COPYING
MANIFEST.in
README.md
setup.py
dememefy/__init__.py
dememefy/__main__.py
dememefy/cli.py
dememefy/image.py
dememefy/text.py
dememefy/tweak.py
dememefy.egg-info/PKG-INFO
dememefy.egg-info/SOURCES.txt
dememefy.egg-info/dependency_links.txt
dememefy.egg-info/entry_points.txt
dememefy.egg-info/requires.txt
dememefy.egg-info/top_level.txt
dememefy/fonts/Symbola.ttf
dememefy/posts/__init__.py
dememefy/posts/posts.py
dememefy/posts/reddit/__init__.py
dememefy/posts/reddit/posts.py