Metadata-Version: 2.1
Name: dememefy
Version: 1.2.6
Summary: dememefy - make pics fun again
Home-page: https://github.com/pinktoxin/dememefy
Author: pinktoxin
Author-email: pinktoxindev@gmail.com
License: UNKNOWN
Platform: UNKNOWN
Requires-Python: >=3.7
License-File: COPYING
